flapjack_stack/__init__.py
flapjack_stack/flapjack_stack.py
flapjack_stack-1.0.0.dist-info/DESCRIPTION.rst
flapjack_stack-1.0.0.dist-info/METADATA
flapjack_stack-1.0.0.dist-info/RECORD
flapjack_stack-1.0.0.dist-info/WHEEL
flapjack_stack-1.0.0.dist-info/metadata.json
flapjack_stack-1.0.0.dist-info/top_level.txt
