Metadata-Version: 2.0
Name: flapjack-stack
Version: 1.0.0
Summary: A multi-layered approach to settings
Home-page: https://github.com/juiceinc/flapjack_stack
Author: Jason Myers
Author-email: jason.myers@juiceanalytics.com
License: License :: OSI Approved :: MIT License
Keywords: settings flapjack_stack
Platform: UNKNOWN
Classifier: Development Status :: 5 - Production/Stable
Classifier: Intended Audience :: Developers
Classifier: Programming Language :: Python :: 2.7
Classifier: Programming Language :: Python :: 3.4
Classifier: Programming Language :: Python :: 3.5
Classifier: Programming Language :: Python :: 3.6
Requires-Dist: PyYaml (==3.12)
